hello_world/__init__.py
eyad123-0.3.dist-info/METADATA
eyad123-0.3.dist-info/WHEEL
eyad123-0.3.dist-info/top_level.txt
eyad123-0.3.dist-info/RECORD
