Metadata-Version: 2.4
Name: eyad123
Version: 0.3
Summary: My hello world package that depends on Flask
Author: Eyad123
Classifier: Programming Language :: Python :: 3
Classifier: Operating System :: OS Independent
Requires-Python: >=3.6
Requires-Dist: flask
Dynamic: author
Dynamic: classifier
Dynamic: description
Dynamic: description-content-type
Dynamic: requires-dist
Dynamic: requires-python
Dynamic: summary
